Metadata-Version: 1.1
Name: wcscmd
Version: 1.0.2
Summary: Wangsu Cloud Storage Command Tool
Home-page: https://wcs.chinanetcenter.com/document/SDK
Author: https://github.com/Wangsu-Cloud-Storage
Author-email: cdn_team_storage_wcs@chinanetcenter.com
License: MIT
Platform: UNKNOWN
Classifier: Intended Audience :: Developers
Classifier: Operating System :: OS Independent
Classifier: Programming Language :: Python
Classifier: Programming Language :: Python :: 2
Classifier: Programming Language :: Python :: 2.6
Classifier: Programming Language :: Python :: 2.7
Classifier: Programming Language :: Python :: 3
Classifier: Programming Language :: Python :: 3.3
Classifier: Programming Language :: Python :: 3.4
Classifier: Programming Language :: Python :: 3.5
Classifier: Topic :: Internet :: WWW/HTTP :: Dynamic Content
Classifier: Topic :: Software Development :: Libraries :: Python Modules
